{
    "_database" : {                          
        "mol_db" : "", 
        "format" : "",
        "github" : "",
        "ref_values" : "",
        "mdft_output": "",
        "values_to_parse" : {
            "_value" : {
                "label" : ""
            }
        },
        "plots" : {
            "plotsvs" : {
                "_plot" : {
                    "x" : "",
                    "y" : []
                }
            },
            "plotserrdistrib" : {
                "_plot" : {
                    "x" : "",
                    "y" : [],
                    "filename" : ""
                }
            },
            "plotsby" : {
                "_plot" : {
                    "x" : "",
                    "y" : [],
                    "cat_column" : ""
                }
            },
            "unit" : ""
        }
    }     
}
